MANIFEST.in
README.md
setup.py
Thorreznou.egg-info/PKG-INFO
Thorreznou.egg-info/SOURCES.txt
Thorreznou.egg-info/dependency_links.txt
Thorreznou.egg-info/requires.txt
Thorreznou.egg-info/top_level.txt
src/thorreznou/EDA.py
src/thorreznou/ML.py
src/thorreznou/VIZ.py
src/thorreznou/__init__.py
src/thorreznou/data/viz/corazon_visualizeME.png
src/thorreznou/data/viz/dino_steg_visualizeME.jpg
src/thorreznou/data/viz/estrella-silueta_visualizeME.png
src/thorreznou/data/viz/hashtag-silueta_visualizeME.png
src/thorreznou/data/viz/seaborn_color_list.csv
src/thorreznou/data/viz/seahorse_visualizeME.jpg