Metadata-Version: 2.1
Name: Thorreznou
Version: 0.1.13
Summary: Thorreznou.
Home-page: https://github.com/erfederuiz/thorreznou
Author: The Bridge Data Science Team 1121
Author-email: Thorreznou@gmail.com
License: UNKNOWN
Platform: UNKNOWN
Classifier: Programming Language :: Python :: 3
Classifier: License :: OSI Approved :: MIT License
Classifier: Operating System :: OS Independent
Requires-Python: >=3.7
